[
  { "name": "Audi A1", "year": 2020, "seats": 5, "cost": 22000, "type": "Gasoline" },
  { "name": "Audi A3", "year": 2022, "seats": 5, "cost": 27000, "type": "Hybrid" },
  { "name": "Audi A4", "year": 2021, "seats": 5, "cost": 35000, "type": "Diesel" },
  { "name": "Audi A5", "year": 2023, "seats": 5, "cost": 42000, "type": "Gasoline" },
  { "name": "Audi A6", "year": 2019, "seats": 5, "cost": 48000, "type": "Diesel" },
  { "name": "Audi Q2", "year": 2022, "seats": 5, "cost": 30000, "type": "Hybrid" },
  { "name": "Audi Q3", "year": 2020, "seats": 5, "cost": 32000, "type": "Gasoline" },
  { "name": "Audi Q5", "year": 2021, "seats": 5, "cost": 45000, "type": "Diesel" },
  { "name": "Audi Q7", "year": 2023, "seats": 7, "cost": 68000, "type": "Hybrid" },
  { "name": "Audi e-tron", "year": 2024, "seats": 5, "cost": 70000, "type": "Electric" },
  { "name": "BMW Serie 1", "year": 2020, "seats": 5, "cost": 24000, "type": "Gasoline" },
  { "name": "BMW Serie 2", "year": 2021, "seats": 4, "cost": 30000, "type": "Diesel" },
  { "name": "BMW Serie 3", "year": 2019, "seats": 5, "cost": 35000, "type": "Hybrid" },
  { "name": "BMW Serie 4", "year": 2022, "seats": 4, "cost": 42000, "type": "Gasoline" },
  { "name": "BMW Serie 5", "year": 2021, "seats": 5, "cost": 52000, "type": "Diesel" },
  { "name": "BMW Serie 7", "year": 2023, "seats": 5, "cost": 80000, "type": "Hybrid" },
  { "name": "BMW X1", "year": 2020, "seats": 5, "cost": 32000, "type": "Diesel" },
  { "name": "BMW X3", "year": 2022, "seats": 5, "cost": 45000, "type": "Hybrid" },
  { "name": "BMW X5", "year": 2023, "seats": 5, "cost": 65000, "type": "Hybrid" },
  { "name": "BMW iX3", "year": 2024, "seats": 5, "cost": 60000, "type": "Electric" },
  { "name": "Porsche 911", "year": 2024, "seats": 4, "cost": 120000, "type": "Gasoline" },
  { "name": "Porsche Cayenne", "year": 2022, "seats": 5, "cost": 85000, "type": "Hybrid" },
  { "name": "Porsche Macan", "year": 2023, "seats": 5, "cost": 75000, "type": "Gasoline" },
  { "name": "Porsche Panamera", "year": 2020, "seats": 4, "cost": 95000, "type": "Hybrid" },
  { "name": "Porsche Taycan", "year": 2023, "seats": 4, "cost": 110000, "type": "Electric" },
  { "name": "Porsche Boxster", "year": 2021, "seats": 2, "cost": 72000, "type": "Gasoline" },
  { "name": "Porsche Cayman", "year": 2020, "seats": 2, "cost": 69000, "type": "Gasoline" },
  { "name": "Porsche 918", "year": 2015, "seats": 2, "cost": 1400000, "type": "Hybrid" },
  { "name": "Porsche Carrera GT", "year": 2018, "seats": 2, "cost": 800000, "type": "Gasoline" },
  { "name": "Porsche 959", "year": 2016, "seats": 2, "cost": 1200000, "type": "Gasoline" },
  { "name": "Mercedes-Benz A-Class", "year": 2020, "seats": 5, "cost": 26000, "type": "Gasoline" },
  { "name": "Mercedes-Benz B-Class", "year": 2021, "seats": 5, "cost": 30000, "type": "Diesel" },
  { "name": "Mercedes-Benz C-Class", "year": 2022, "seats": 5, "cost": 42000, "type": "Hybrid" },
  { "name": "Mercedes-Benz E-Class", "year": 2023, "seats": 5, "cost": 60000, "type": "Hybrid" },
  { "name": "Mercedes-Benz S-Class", "year": 2024, "seats": 5, "cost": 100000, "type": "Hybrid" },
  { "name": "Mercedes-Benz GLA", "year": 2021, "seats": 5, "cost": 38000, "type": "Gasoline" },
  { "name": "Mercedes-Benz GLC", "year": 2022, "seats": 5, "cost": 50000, "type": "Diesel" },
  { "name": "Mercedes-Benz GLE", "year": 2020, "seats": 7, "cost": 70000, "type": "Hybrid" },
  { "name": "Mercedes-Benz EQC", "year": 2023, "seats": 5, "cost": 75000, "type": "Electric" },
  { "name": "Mercedes-Benz EQS", "year": 2024, "seats": 5, "cost": 115000, "type": "Electric" },
  { "name": "Audi TT", "year": 2020, "seats": 2, "cost": 43000, "type": "Gasoline" },
  { "name": "Audi RS3", "year": 2023, "seats": 5, "cost": 62000, "type": "Gasoline" },
  { "name": "Audi RS6", "year": 2024, "seats": 5, "cost": 120000, "type": "Hybrid" },
  { "name": "BMW M3", "year": 2021, "seats": 5, "cost": 90000, "type": "Gasoline" },
  { "name": "BMW M5", "year": 2023, "seats": 5, "cost": 110000, "type": "Hybrid" },
  { "name": "BMW i3", "year": 2019, "seats": 4, "cost": 36000, "type": "Electric" },
  { "name": "BMW i4", "year": 2022, "seats": 5, "cost": 58000, "type": "Electric" },
  { "name": "Porsche Mission E", "year": 2024, "seats": 4, "cost": 130000, "type": "Electric" },
  { "name": "Mercedes-Benz EQB", "year": 2022, "seats": 7, "cost": 60000, "type": "Electric" },
  { "name": "Mercedes-Benz GLB", "year": 2021, "seats": 7, "cost": 45000, "type": "Diesel" },
  { "name": "Tesla Model 3", "year": 2023, "seats": 5, "cost": 45000, "type": "Electric" },
  { "name": "Tesla Model Y", "year": 2024, "seats": 7, "cost": 55000, "type": "Electric" },
  { "name": "Tesla Model S", "year": 2022, "seats": 5, "cost": 85000, "type": "Electric" },
  { "name": "Tesla Model X", "year": 2021, "seats": 7, "cost": 95000, "type": "Electric" },
  { "name": "Toyota Camry", "year": 2023, "seats": 5, "cost": 30000, "type": "Hybrid" },
  { "name": "Toyota Corolla", "year": 2024, "seats": 5, "cost": 25000, "type": "Gasoline" },
  { "name": "Toyota RAV4", "year": 2022, "seats": 5, "cost": 35000, "type": "Hybrid" },
  { "name": "Toyota Highlander", "year": 2021, "seats": 7, "cost": 40000, "type": "Gasoline" },
  { "name": "Honda Civic", "year": 2023, "seats": 5, "cost": 24000, "type": "Gasoline" },
  { "name": "Honda CR-V", "year": 2024, "seats": 5, "cost": 32000, "type": "Hybrid" },
  { "name": "Honda Accord", "year": 2022, "seats": 5, "cost": 28000, "type": "Gasoline" },
  { "name": "Ford Focus", "year": 2021, "seats": 5, "cost": 21000, "type": "Gasoline" },
  { "name": "Ford Kuga", "year": 2023, "seats": 5, "cost": 33000, "type": "Hybrid" },
  { "name": "Ford Mustang", "year": 2024, "seats": 4, "cost": 55000, "type": "Gasoline" },
  { "name": "Volkswagen Golf", "year": 2022, "seats": 5, "cost": 26000, "type": "Gasoline" },
  { "name": "Volkswagen Tiguan", "year": 2023, "seats": 5, "cost": 38000, "type": "Diesel" },
  { "name": "Volkswagen ID.4", "year": 2024, "seats": 5, "cost": 48000, "type": "Electric" },
  { "name": "Nissan Qashqai", "year": 2022, "seats": 5, "cost": 29000, "type": "Gasoline" },
  { "name": "Nissan Leaf", "year": 2023, "seats": 5, "cost": 35000, "type": "Electric" },
  { "name": "Hyundai Tucson", "year": 2024, "seats": 5, "cost": 31000, "type": "Hybrid" },
  { "name": "Kia Sportage", "year": 2023, "seats": 5, "cost": 30000, "type": "Hybrid" },
  { "name": "Volvo XC60", "year": 2022, "seats": 5, "cost": 50000, "type": "Hybrid" },
  { "name": "Volvo S60", "year": 2023, "seats": 5, "cost": 45000, "type": "Gasoline" },
  { "name": "Subaru Outback", "year": 2024, "seats": 5, "cost": 37000, "type": "Gasoline" },
  { "name": "Mazda CX-5", "year": 2022, "seats": 5, "cost": 28000, "type": "Gasoline" },
  { "name": "Chevrolet Equinox", "year": 2023, "seats": 5, "cost": 27000, "type": "Gasoline" },
  { "name": "Jeep Wrangler", "year": 2024, "seats": 4, "cost": 40000, "type": "Gasoline" },
  { "name": "Land Rover Defender", "year": 2023, "seats": 7, "cost": 70000, "type": "Diesel" },
  { "name": "Fiat 500", "year": 2022, "seats": 4, "cost": 18000, "type": "Gasoline" },
  { "name": "Peugeot 3008", "year": 2023, "seats": 5, "cost": 34000, "type": "Hybrid" },
  { "name": "Renault Clio", "year": 2024, "seats": 5, "cost": 19000, "type": "Gasoline" },
  { "name": "Skoda Octavia", "year": 2022, "seats": 5, "cost": 27000, "type": "Diesel" },
  { "name": "Citroen C3 Aircross", "year": 2023, "seats": 5, "cost": 22000, "type": "Gasoline" },
  { "name": "Seat Leon", "year": 2024, "seats": 5, "cost": 25000, "type": "Gasoline" },
  { "name": "Mitsubishi Outlander", "year": 2022, "seats": 7, "cost": 36000, "type": "Hybrid" },
  { "name": "Audi A7", "year": 2023, "seats": 5, "cost": 65000, "type": "Hybrid" },
  { "name": "Audi A8", "year": 2024, "seats": 5, "cost": 90000, "type": "Hybrid" },
  { "name": "Audi Q8", "year": 2023, "seats": 5, "cost": 78000, "type": "Hybrid" },
  { "name": "BMW X6", "year": 2022, "seats": 5, "cost": 72000, "type": "Diesel" },
  { "name": "BMW X7", "year": 2023, "seats": 7, "cost": 88000, "type": "Hybrid" },
  { "name": "Mercedes-Benz CLA", "year": 2022, "seats": 5, "cost": 39000, "type": "Gasoline" },
  { "name": "Mercedes-Benz GLC Coupe", "year": 2023, "seats": 5, "cost": 55000, "type": "Diesel" },
  { "name": "Porsche 718 Cayman", "year": 2023, "seats": 2, "cost": 75000, "type": "Gasoline" },
  { "name": "Tesla Cybertruck", "year": 2025, "seats": 6, "cost": 79000, "type": "Electric" },
  { "name": "Toyota C-HR", "year": 2023, "seats": 5, "cost": 27000, "type": "Hybrid" },
  { "name": "Honda HR-V", "year": 2024, "seats": 5, "cost": 26000, "type": "Gasoline" },
  { "name": "Ford Bronco", "year": 2023, "seats": 5, "cost": 35000, "type": "Gasoline" },
  { "name": "Volkswagen Jetta", "year": 2022, "seats": 5, "cost": 23000, "type": "Gasoline" },
  { "name": "Nissan Rogue", "year": 2023, "seats": 5, "cost": 28000, "type": "Gasoline" },
  { "name": "Hyundai Kona Electric", "year": 2024, "seats": 5, "cost": 38000, "type": "Electric" },
  { "name": "Kia Sorento", "year": 2022, "seats": 7, "cost": 39000, "type": "Hybrid" },
  { "name": "Volvo S90", "year": 2023, "seats": 5, "cost": 58000, "type": "Hybrid" },
  { "name": "Subaru Forester", "year": 2024, "seats": 5, "cost": 30000, "type": "Gasoline" },
  { "name": "Mazda 3", "year": 2022, "seats": 5, "cost": 24000, "type": "Gasoline" },
  { "name": "Chevrolet Colorado", "year": 2023, "seats": 5, "cost": 30000, "type": "Diesel" },
  { "name": "Jeep Grand Cherokee", "year": 2024, "seats": 5, "cost": 45000, "type": "Hybrid" },
  { "name": "Land Rover Range Rover Sport", "year": 2023, "seats": 5, "cost": 85000, "type": "Hybrid" },
  { "name": "Fiat Panda", "year": 2022, "seats": 5, "cost": 15000, "type": "Gasoline" },
  { "name": "Peugeot 208", "year": 2023, "seats": 5, "cost": 23000, "type": "Gasoline" },
  { "name": "Renault Captur", "year": 2024, "seats": 5, "cost": 26000, "type": "Hybrid" },
  { "name": "Skoda Superb", "year": 2022, "seats": 5, "cost": 32000, "type": "Diesel" },
  { "name": "Citroen C4", "year": 2023, "seats": 5, "cost": 28000, "type": "Gasoline" },
  { "name": "Seat Arona", "year": 2024, "seats": 5, "cost": 21000, "type": "Gasoline" },
  { "name": "Mitsubishi Eclipse Cross", "year": 2022, "seats": 5, "cost": 29000, "type": "Hybrid" }
]